clmetrics-0.0.1.dist-info/DESCRIPTION.rst
clmetrics-0.0.1.dist-info/METADATA
clmetrics-0.0.1.dist-info/RECORD
clmetrics-0.0.1.dist-info/WHEEL
clmetrics-0.0.1.dist-info/metadata.json
clmetrics-0.0.1.dist-info/top_level.txt
metrics/__init__.py
metrics/metrics.py
