Metadata-Version: 2.0
Name: clmetrics
Version: 0.0.1
Summary: Package for evaluate clusters
Home-page: https://github.com/weslleylc/metrics
Author: Weslley Caldas
Author-email: weslleylc@gmail.com
License: Copyright (c) 2017, Weslley Caldas
